odoo10_addon_l10n_nl_cbs_export-10.0.1.0.0-py2.7-nspkg.pth
odoo/addons/l10n_nl_cbs_export/README.rst
odoo/addons/l10n_nl_cbs_export/__init__.py
odoo/addons/l10n_nl_cbs_export/__manifest__.py
odoo/addons/l10n_nl_cbs_export/data/cbs_export_file_sequence.xml
odoo/addons/l10n_nl_cbs_export/data/cron_process_cbs_export.xml
odoo/addons/l10n_nl_cbs_export/doc/Codelijst_1Goederenstroom.pdf
odoo/addons/l10n_nl_cbs_export/doc/Codelijst_2Vervoerwijze.pdf
odoo/addons/l10n_nl_cbs_export/doc/Codelijst_4Statistisch Stelsel.pdf
odoo/addons/l10n_nl_cbs_export/doc/Codelijst_5Transactie.pdf
odoo/addons/l10n_nl_cbs_export/doc/RLO_2017_NL.pdf
odoo/addons/l10n_nl_cbs_export/doc/file-layout.xlsx
odoo/addons/l10n_nl_cbs_export/i18n/nl.po
odoo/addons/l10n_nl_cbs_export/models/__init__.py
odoo/addons/l10n_nl_cbs_export/models/account_invoice.py
odoo/addons/l10n_nl_cbs_export/models/cbs_export_file.py
odoo/addons/l10n_nl_cbs_export/security/cbs_export_file_security.xml
odoo/addons/l10n_nl_cbs_export/security/ir.model.access.csv
odoo/addons/l10n_nl_cbs_export/static/description/icon.png
odoo/addons/l10n_nl_cbs_export/tests/__init__.py
odoo/addons/l10n_nl_cbs_export/tests/test_cbs_export_file.py
odoo/addons/l10n_nl_cbs_export/view/cbs_export_file_view.xml
odoo10_addon_l10n_nl_cbs_export-10.0.1.0.0.dist-info/DESCRIPTION.rst
odoo10_addon_l10n_nl_cbs_export-10.0.1.0.0.dist-info/METADATA
odoo10_addon_l10n_nl_cbs_export-10.0.1.0.0.dist-info/RECORD
odoo10_addon_l10n_nl_cbs_export-10.0.1.0.0.dist-info/WHEEL
odoo10_addon_l10n_nl_cbs_export-10.0.1.0.0.dist-info/metadata.json
odoo10_addon_l10n_nl_cbs_export-10.0.1.0.0.dist-info/namespace_packages.txt
odoo10_addon_l10n_nl_cbs_export-10.0.1.0.0.dist-info/top_level.txt
